README
setup.py
python_rdio.egg-info/PKG-INFO
python_rdio.egg-info/SOURCES.txt
python_rdio.egg-info/dependency_links.txt
python_rdio.egg-info/requires.txt
python_rdio.egg-info/top_level.txt
rdio/__init__.py
rdio/rdio.py