Metadata-Version: 1.0
Name: python-rdio
Version: 0.6
Summary: An unofficial wrapper for the Rdio API.
Home-page: http://github.com/kreeger/python-rdio
Author: Benjamin Kreeger
Author-email: benjaminkreeger@gmail.com
License: MIT
Keywords: api rpc rdio music
Platform: any
